[
  {
    "index": 0,
    "start": 0.0,
    "end": 14.0,
    "text": "We worry so much about tomorrow. We forget about today."
  },
  {
    "index": 1,
    "start": 26.0,
    "end": 28.0,
    "text": "I want to check out that store."
  },
  {
    "index": 2,
    "start": 31.0,
    "end": 34.0,
    "text": "I love your necklace by the way."
  },
  {
    "index": 3,
    "start": 34.0,
    "end": 36.0,
    "text": "Thank you."
  },
  {
    "index": 4,
    "start": 37.0,
    "end": 39.0,
    "text": "I'm going to the store."
  },
  {
    "index": 5,
    "start": 53.0,
    "end": 54.0,
    "text": "Oh my god!"
  },
  {
    "index": 6,
    "start": 54.0,
    "end": 56.0,
    "text": "I'm so happy to see you."
  },
  {
    "index": 7,
    "start": 56.0,
    "end": 58.0,
    "text": "Oh my god!"
  },
  {
    "index": 8,
    "start": 67.0,
    "end": 69.0,
    "text": "Hi!"
  },
  {
    "index": 9,
    "start": 81.0,
    "end": 83.0,
    "text": "Thank you."
  },
  {
    "index": 10,
    "start": 90.0,
    "end": 94.0,
    "text": "We spend so much time thinking about tomorrow."
  },
  {
    "index": 11,
    "start": 94.0,
    "end": 96.0,
    "text": "Forget about today."
  },
  {
    "index": 12,
    "start": 96.0,
    "end": 98.0,
    "text": "I'm so sorry."
  },
  {
    "index": 13,
    "start": 98.0,
    "end": 100.0,
    "text": "I'm sorry."
  }
]