[
  {
    "index": 0,
    "start": 0.0,
    "end": 4.5,
    "text": "Thousands of the world's best sales teams are generating billions in pipeline with Nooks."
  },
  {
    "index": 1,
    "start": 4.5,
    "end": 10.5,
    "text": "Today, I'm excited to announce our biggest evolution yet, the Agent Workspace, for Intelligent Outbound."
  },
  {
    "index": 2,
    "start": 11.5,
    "end": 18.0,
    "text": "Most sales teams still run on legacy sequencing tools like Outreach and Salesloft, built for a world where most tasks were manual."
  },
  {
    "index": 3,
    "start": 18.0,
    "end": 24.5,
    "text": "Our Agent Workspace has all the core features of these legacy tools, sequences, tasks, email deliverability,"
  },
  {
    "index": 4,
    "start": 24.5,
    "end": 28.5,
    "text": "but reimagined to combine the best of human judgment with AI execution."
  },
  {
    "index": 5,
    "start": 31.0,
    "end": 37.0,
    "text": "Every day, Nooks agents monitor your accounts, pulling deep research from your own data, linked in, and the web."
  },
  {
    "index": 6,
    "start": 37.0,
    "end": 39.5,
    "text": "They turn that research into actionable buying signals."
  },
  {
    "index": 7,
    "start": 39.5,
    "end": 44.5,
    "text": "Here, an agent discovered an upcoming competitive renewal, surfaced from a previous call recording."
  },
  {
    "index": 8,
    "start": 44.5,
    "end": 48.5,
    "text": "It recommends prospects by analyzing prior conversations and mapping the org,"
  },
  {
    "index": 9,
    "start": 48.5,
    "end": 52.0,
    "text": "enriches them with a contact data waterfall across dozens of providers,"
  },
  {
    "index": 10,
    "start": 52.0,
    "end": 56.5,
    "text": "and suggests sequences with personalized emails that you can edit and approve before sending."
  },
  {
    "index": 11,
    "start": 56.5,
    "end": 61.0,
    "text": "Finally, you can push these leads to our AI dialer for efficient, live conversations,"
  },
  {
    "index": 12,
    "start": 61.0,
    "end": 64.0,
    "text": "enabled by AI research and real-time battle cards."
  },
  {
    "index": 13,
    "start": 65.5,
    "end": 69.0,
    "text": "As reps give feedback, like approving prospects and editing emails,"
  },
  {
    "index": 14,
    "start": 69.0,
    "end": 71.5,
    "text": "agents learn to be more autonomous over time."
  },
  {
    "index": 15,
    "start": 71.5,
    "end": 77.0,
    "text": "In our AI studio, you can orchestrate agents into outbound plays that react real-time to the market."
  },
  {
    "index": 16,
    "start": 77.0,
    "end": 80.5,
    "text": "From a VP joining a new company, to a new product launch,"
  },
  {
    "index": 17,
    "start": 80.5,
    "end": 83.5,
    "text": "agents detect and trigger the right message at the right time."
  },
  {
    "index": 18,
    "start": 84.0,
    "end": 87.0,
    "text": "Until today, this required dozens of disconnected tools,"
  },
  {
    "index": 19,
    "start": 87.0,
    "end": 90.0,
    "text": "but Nooks consolidates everything into one unified workspace."
  },
  {
    "index": 20,
    "start": 90.0,
    "end": 93.0,
    "text": "And while others are using AI to replace people,"
  },
  {
    "index": 21,
    "start": 93.0,
    "end": 98.0,
    "text": "we believe your best reps, working together with AI, can push the boundaries of what's possible."
  },
  {
    "index": 22,
    "start": 99.0,
    "end": 103.0,
    "text": "Leading sales teams from sophisticated enterprises to the fastest-growing startups"
  },
  {
    "index": 23,
    "start": 103.0,
    "end": 106.0,
    "text": "have already made the switch and seen incredible results."
  },
  {
    "index": 24,
    "start": 106.0,
    "end": 109.0,
    "text": "Come join them and enter the era of intelligent outbound."
  },
  {
    "index": 25,
    "start": 113.5,
    "end": 116.0,
    "text": "Thank you."
  }
]